alibabacloud_xtee20210910/__init__.py
alibabacloud_xtee20210910/client.py
alibabacloud_xtee20210910/models/__init__.py
alibabacloud_xtee20210910/models/_add_sample_data_by_csv_request.py
alibabacloud_xtee20210910/models/_add_sample_data_by_csv_response.py
alibabacloud_xtee20210910/models/_add_sample_data_by_csv_response_body.py
alibabacloud_xtee20210910/models/_add_sample_data_by_text_request.py
alibabacloud_xtee20210910/models/_add_sample_data_by_text_response.py
alibabacloud_xtee20210910/models/_add_sample_data_by_text_response_body.py
alibabacloud_xtee20210910/models/_batch_delete_sample_data_request.py
alibabacloud_xtee20210910/models/_batch_delete_sample_data_response.py
alibabacloud_xtee20210910/models/_batch_delete_sample_data_response_body.py
alibabacloud_xtee20210910/models/_bind_variable_request.py
alibabacloud_xtee20210910/models/_bind_variable_response.py
alibabacloud_xtee20210910/models/_bind_variable_response_body.py
alibabacloud_xtee20210910/models/_check_copy_rule_variable_request.py
alibabacloud_xtee20210910/models/_check_copy_rule_variable_response.py
alibabacloud_xtee20210910/models/_check_copy_rule_variable_response_body.py
alibabacloud_xtee20210910/models/_check_cust_variable_limit_request.py
alibabacloud_xtee20210910/models/_check_cust_variable_limit_response.py
alibabacloud_xtee20210910/models/_check_cust_variable_limit_response_body.py
alibabacloud_xtee20210910/models/_check_expression_variable_limit_request.py
alibabacloud_xtee20210910/models/_check_expression_variable_limit_response.py
alibabacloud_xtee20210910/models/_check_expression_variable_limit_response_body.py
alibabacloud_xtee20210910/models/_check_field_limit_request.py
alibabacloud_xtee20210910/models/_check_field_limit_response.py
alibabacloud_xtee20210910/models/_check_field_limit_response_body.py
alibabacloud_xtee20210910/models/_check_usage_variable_request.py
alibabacloud_xtee20210910/models/_check_usage_variable_response.py
alibabacloud_xtee20210910-2.2.1.dist-info/LICENSE
alibabacloud_xtee20210910-2.2.1.dist-info/METADATA
alibabacloud_xtee20210910-2.2.1.dist-info/WHEEL
alibabacloud_xtee20210910-2.2.1.dist-info/top_level.txt
alibabacloud_xtee20210910-2.2.1.dist-info/RECORD
